setup.py
bin/spate-list-jobs
bin/spate-show-jobs
lib/__init__.py
lib/core.py
lib/errors.py
lib/paths.py
lib/templating.py
lib/utils.py
lib/io/__init__.py
lib/io/base.py
lib/io/drake.py
lib/io/graphviz.py
lib/io/makefile.py
lib/io/makeflow.py
lib/io/shell.py
lib/io/slurm.py
lib/io/torque.py
lib/io/utils.py
spate.egg-info/PKG-INFO
spate.egg-info/SOURCES.txt
spate.egg-info/dependency_links.txt
spate.egg-info/requires.txt
spate.egg-info/top_level.txt