Metadata-Version: 1.1
Name: spate
Version: 0.2.3
Summary: Lightweight workflow composition and generation engine
Home-page: https://github.com/ajmazurie/spate
Author: Aurelien Mazurie
Author-email: ajmazurie@oenone.net
License: UNKNOWN
Download-URL: https://github.com/ajmazurie/spate/archive/0.2.3.zip
Platform: UNKNOWN
Classifier: Development Status :: 4 - Beta
Classifier: Environment :: Console
Classifier: License :: OSI Approved :: MIT License
Classifier: Operating System :: OS Independent
Classifier: Programming Language :: Python :: 2.7
Classifier: Topic :: System :: Distributed Computing
